resourcecode/__init__.py
resourcecode/__version__.py
resourcecode/client.py
resourcecode/exceptions.py
resourcecode/io.py
resourcecode/plotly_theme.py
resourcecode/utils.py
resourcecode/data/__init__.py
resourcecode/data/coastline.feather
resourcecode/data/grid_FIELD.feather
resourcecode/data/grid_SPEC.feather
resourcecode/data/islands.feather
resourcecode/data/netcdf_description.json
resourcecode/data/triangles.feather
resourcecode/data/variables.feather
resourcecode/eva/__init__.py
resourcecode/eva/censgaussfit.py
resourcecode/eva/extrema.py
resourcecode/eva/huseby.py
resourcecode/eva/simulation.py
resourcecode/opsplanning/__init__.py
resourcecode/producible_assessment/__init__.py
resourcecode/producible_assessment/main.py
resourcecode/producible_assessment/Inputs/Frequencies.csv
resourcecode/producible_assessment/Inputs/HsTptimeseries.csv
resourcecode/producible_assessment/Inputs/PTO_values.csv
resourcecode/producible_assessment/Inputs/capture_width.csv
resourcecode/resassess/__init__.py
resourcecode/spectrum/__init__.py
resourcecode/spectrum/compute_parameters.py
resourcecode/spectrum/convert2D1D.py
resourcecode/spectrum/dispersion.py
resourcecode/spectrum/download_data.py
resourcecode/spectrum/jonswap.py
resourcecode/spectrum/plots.py
resourcecode/weatherwindow/__init__.py
resourcecode/weatherwindow/weatherwindow.py
resourcecode-1.3.1.data/data/etc/resourcecode/config.ini
resourcecode-1.3.1.dist-info/licenses/COPYING
resourcecode-1.3.1.dist-info/licenses/LICENSE
tests/__init__.py
tests/test_client.py
tests/test_data.py
tests/test_eva.py
tests/test_netfcd.py
tests/test_opsplanning.py
tests/test_producible_assessment.py
tests/test_resassess.py
tests/test_spectrum.py
tests/test_utils.py
tests/test_weather_window.py
tests/data/timeseries_fp.json
tests/data/timeseries_hs.json
tests/data/timeseries_uust.json
tests/data/censgaussfit/input_0.csv
tests/data/censgaussfit/output_0.csv
tests/data/huseby/input_0.csv
tests/data/huseby/output_0.csv
tests/data/huseby/output_1.csv
tests/data/opsplanning/input.csv
tests/data/resassess/df_average_energy.csv
resourcecode-1.3.1.dist-info/METADATA
resourcecode-1.3.1.dist-info/WHEEL
resourcecode-1.3.1.dist-info/top_level.txt
resourcecode-1.3.1.dist-info/RECORD
