Metadata-Version: 2.4
Name: resourcecode
Version: 1.3.1
Summary: The ResourceCODE Marine Data Toolbox is a python package to facilitate the access to recent hindcast database of sea-state , along with a set of state-of-the-art methods for data analysis.
Home-page: https://gitlab.ifremer.fr/resourcecode/resourcecode
Author: Nicolas Raillard (IFREMER, Brest)
Author-email: nicolas.raillard@ifremer.fr
License: GPL-v3.0
Project-URL: GitHub, https://github.com/Resourcecode-project/py-resourcecode
Project-URL: Web Portal, https://resourcecode.ifremer.fr
Project-URL: PyPI, https://pypi.org/project/resourcecode
Keywords: statistics,extreme,extreme value analysis,eva,coastal,ocean,marine,environmental,engineering,renewable,MRE,offshore,data,hindcast
Classifier: Development Status :: 5 - Production/Stable
Classifier: Intended Audience :: Science/Research
Classifier: Intended Audience :: Developers
Classifier: Programming Language :: Python
Classifier: Programming Language :: Python :: 3.9
Classifier: Programming Language :: Python :: 3.10
Classifier: Programming Language :: Python :: 3.11
Classifier: Programming Language :: Python :: 3.12
Classifier: Programming Language :: Python :: 3 :: Only
Classifier: Operating System :: OS Independent
Classifier: License :: OSI Approved :: GNU General Public License v3 (GPLv3)
Classifier: Topic :: Scientific/Engineering
Classifier: Topic :: Scientific/Engineering :: Mathematics
Classifier: Topic :: Scientific/Engineering :: Physics
Requires-Python: >=3.9, <3.13
License-File: LICENSE
License-File: COPYING
Requires-Dist: pandas<3.0.0,>=1.0.0
Requires-Dist: requests>=2.23.0
Requires-Dist: numpy<2.0.0,>=1.20.1
Requires-Dist: scipy<1.14.0,>=1.6.1
Requires-Dist: pyextremes>=2.0.0
Requires-Dist: pytest>=7.0.0
Requires-Dist: pyarrow>=6.0.0
Requires-Dist: plotly>=4.12.0
Requires-Dist: numexpr>=2.7.0
Requires-Dist: xarray>=0.19.0
Requires-Dist: netCDF4>=1.6.0
Dynamic: author
Dynamic: author-email
Dynamic: classifier
Dynamic: description
Dynamic: description-content-type
Dynamic: home-page
Dynamic: keywords
Dynamic: license
Dynamic: license-file
Dynamic: project-url
Dynamic: requires-dist
Dynamic: requires-python
Dynamic: summary
